fdiff/__init__.py
fdiff/__main__.py
fdiff/aio.py
fdiff/color.py
fdiff/diff.py
fdiff/exceptions.py
fdiff/remote.py
fdiff/textiter.py
fdiff/utils.py
fdiff-3.0.0.dist-info/LICENSE
fdiff-3.0.0.dist-info/METADATA
fdiff-3.0.0.dist-info/WHEEL
fdiff-3.0.0.dist-info/entry_points.txt
fdiff-3.0.0.dist-info/top_level.txt
fdiff-3.0.0.dist-info/RECORD
