Metadata-Version: 2.1
Name: fdiff
Version: 3.0.0
Summary: An OpenType table diff tool for fonts
Home-page: https://github.com/source-foundry/fdiff
Author: Source Foundry Authors
Author-email: chris@sourcefoundry.org
License: Apache License v2.0
Platform: Any
Classifier: Development Status :: 5 - Production/Stable
Classifier: Environment :: Console
Classifier: Intended Audience :: Developers
Classifier: Intended Audience :: End Users/Desktop
Classifier: License :: OSI Approved :: Apache Software License
Classifier: Natural Language :: English
Classifier: Operating System :: OS Independent
Classifier: Programming Language :: Python
Classifier: Programming Language :: Python :: 3
Classifier: Programming Language :: Python :: 3.7
Classifier: Programming Language :: Python :: 3.8
Classifier: Programming Language :: Python :: 3.9
Classifier: Programming Language :: Python :: 3.10
Classifier: Topic :: Multimedia
Requires-Python: >=3.7.0
License-File: LICENSE
Requires-Dist: fontTools (>=4.0.0)
Requires-Dist: aiohttp (>=3.6.0)
Requires-Dist: aiodns (>=2.0.0)
Requires-Dist: aiofiles (>=0.4.0)
Requires-Dist: rich
Provides-Extra: dev
Requires-Dist: coverage ; extra == 'dev'
Requires-Dist: pytest ; extra == 'dev'
Requires-Dist: pytest-asyncio ; extra == 'dev'
Requires-Dist: tox ; extra == 'dev'
Requires-Dist: flake8 ; extra == 'dev'
Requires-Dist: mypy ; extra == 'dev'
Provides-Extra: maintain
Requires-Dist: wheel ; extra == 'maintain'
Requires-Dist: setuptools ; extra == 'maintain'
Requires-Dist: twine ; extra == 'maintain'
